defi_protocols/Aave.py
defi_protocols/Agave.py
defi_protocols/Aura.py
defi_protocols/Azuro.py
defi_protocols/Balancer.py
defi_protocols/Bancor.py
defi_protocols/Compound.py
defi_protocols/Convex.py
defi_protocols/Curve.py
defi_protocols/Element.py
defi_protocols/Elk.py
defi_protocols/Honeyswap.py
defi_protocols/Idle.py
defi_protocols/IronBank.py
defi_protocols/Maker.py
defi_protocols/Notional.py
defi_protocols/QiDao.py
defi_protocols/RealT.py
defi_protocols/Reflexer.py
defi_protocols/SushiSwap.py
defi_protocols/Swapr.py
defi_protocols/Symmetric.py
defi_protocols/UniswapV3.py
defi_protocols/Unit.py
defi_protocols/__init__.py
defi_protocols/config.json
defi_protocols/constants.py
defi_protocols/functions.py
defi_protocols/mStable.py
defi_protocols/uniswapv3helper.py
defi_protocols/db/Aura_db.json
defi_protocols/db/Convex_db.json
defi_protocols/db/SushiSwap_db.json
defi_protocols/db/Symmetric_db.json
defi_protocols/prices/Chainlink.py
defi_protocols/prices/CoinGecko.py
defi_protocols/prices/Zapper.py
defi_protocols/prices/_1inch.py
defi_protocols/prices/__init__.py
defi_protocols/prices/db_functions.py
defi_protocols/prices/prices.py
defi_protocols/prices/token_mapping.json
defi_protocols/util/__init__.py
defi_protocols/util/api.py
defi_protocols/util/enums.py
defi_protocols/util/explorers.py
defi_protocols/util/topic.py
defi_protocols-0.0.9.dist-info/LICENSE
defi_protocols-0.0.9.dist-info/METADATA
defi_protocols-0.0.9.dist-info/WHEEL
defi_protocols-0.0.9.dist-info/top_level.txt
defi_protocols-0.0.9.dist-info/RECORD
