Metadata-Version: 2.1
Name: defi-protocols
Version: 0.0.9
Summary: A simple defi_protocols package
Home-page: https://github.com/KarpatkeyDAO/defi-protocols
Author: dharmendrakariya
Author-email: dharmendra@karpatkey.com
Classifier: Programming Language :: Python :: 3
Classifier: License :: OSI Approved :: MIT License
Classifier: Operating System :: OS Independent
Requires-Python: >=3.6
License-File: LICENSE
Requires-Dist: web3 (>=5.15.0)
Requires-Dist: requests (>=2.28.1)
Requires-Dist: datetime (>=4.7)
Requires-Dist: pathlib (>=1.0.1)
Requires-Dist: eth-abi (>=2.0.0)
Requires-Dist: setuptools (>=65.5.1)
Requires-Dist: tqdm (>=4.64.1)
Requires-Dist: pandas (>=1.3.5)
